test_package/__init__.py
test_package/package_module.py
davdovin_test_package-0.1.0.dist-info/METADATA
davdovin_test_package-0.1.0.dist-info/WHEEL
davdovin_test_package-0.1.0.dist-info/top_level.txt
davdovin_test_package-0.1.0.dist-info/RECORD
