Metadata-Version: 2.4
Name: davdovin_test_package
Version: 0.1.0
Summary: Простой пример пакета
Author: Danil Vdovin
Author-email: davdovin32@gmail.com
Classifier: Programming Language :: Python :: 3
Classifier: License :: OSI Approved :: MIT License
Requires-Python: >=3.7
Dynamic: author
Dynamic: author-email
Dynamic: classifier
Dynamic: requires-python
Dynamic: summary
